django_inlinify/__init__.py
django_inlinify/css_tools.py
django_inlinify/defaults.py
django_inlinify/inlinify.py
django_inlinify/test_settings.py
django_inlinify-0.0.17.dist-info/DESCRIPTION.rst
django_inlinify-0.0.17.dist-info/METADATA
django_inlinify-0.0.17.dist-info/metadata.json
django_inlinify-0.0.17.dist-info/RECORD
django_inlinify-0.0.17.dist-info/top_level.txt
django_inlinify-0.0.17.dist-info/WHEEL
